FreeTAKServer/README.md
FreeTAKServer/__init__.py
FreeTAKServer/components/__init__.py
FreeTAKServer/components/core/__init__.py
FreeTAKServer/components/core/abstract_component/__init__.py
FreeTAKServer/components/core/abstract_component/cot_node.py
FreeTAKServer/components/core/abstract_component/cot_property.py
FreeTAKServer/components/core/abstract_component/domain.py
FreeTAKServer/components/core/abstract_component/telemetry_exporter.py
FreeTAKServer/components/core/core_constants.py
FreeTAKServer/components/core/cot_parser/__init__.py
FreeTAKServer/components/core/cot_parser/abstract_serializer.py
FreeTAKServer/components/core/cot_parser/main_cot_parser.py
FreeTAKServer/components/core/cot_parser/xml_element.py
FreeTAKServer/components/core/cot_parser/xml_serializer.py
FreeTAKServer/components/core/domain/__init__.py
FreeTAKServer/components/core/domain/base/__init__.py
FreeTAKServer/components/core/domain/base/domain_action_mapper.py
FreeTAKServer/components/core/domain/base/domain_health_check.py
FreeTAKServer/components/core/domain/base/domain_metrics_controller.py
FreeTAKServer/components/core/domain/configuration/__init__.py
FreeTAKServer/components/core/domain/configuration/business_rules/serialization_business_rules.json
FreeTAKServer/components/core/domain/configuration/domain_constants.py
FreeTAKServer/components/core/domain/configuration/external_action_mapping.ini
FreeTAKServer/components/core/domain/configuration/internal_action_mapping.ini
FreeTAKServer/components/core/domain/configuration/logging.conf
FreeTAKServer/components/core/domain/configuration/manifest.ini
FreeTAKServer/components/core/domain/configuration/metrics.txt
FreeTAKServer/components/core/domain/controllers/__init__.py
FreeTAKServer/components/core/domain/controllers/cot2525_controller.py
FreeTAKServer/components/core/domain/controllers/dict_to_node_controller.py
FreeTAKServer/components/core/domain/controllers/domain.py
freetakserver-2.2.1.dist-info/LICENSE
freetakserver-2.2.1.dist-info/METADATA
freetakserver-2.2.1.dist-info/WHEEL
freetakserver-2.2.1.dist-info/RECORD
