Metadata-Version: 2.1
Name: FreeTAKServer
Version: 2.2.1
Summary: An open source server for the TAK family of applications.
Author: FreeTAKTeam
Author-email: FreeTakTeam@gmail.com
Requires-Python: >=3.11,<4.0
Classifier: Programming Language :: Python :: 3
Classifier: Programming Language :: Python :: 3.11
Classifier: Programming Language :: Python :: 3.12
Provides-Extra: dev
Provides-Extra: ui
Requires-Dist: Flask (==3.0.2)
Requires-Dist: Flask-Cors (==4.0.0)
Requires-Dist: Flask-HTTPAuth (==4.8.0)
Requires-Dist: Flask-Login (==0.6.3)
Requires-Dist: Flask-SQLAlchemy (==3.1.1)
Requires-Dist: Flask-SocketIO (==5.3.6)
Requires-Dist: FreeTAKServer_UI (==2.1) ; extra == "ui"
Requires-Dist: Jinja2 (==3.1.3)
Requires-Dist: MarkupSafe (==2.1.5)
Requires-Dist: PyJWT
Requires-Dist: PyYAML (==6.0.1)
Requires-Dist: SQLAlchemy (==2.0.29)
Requires-Dist: WTForms (==2.3.3)
Requires-Dist: Werkzeug (==3.0.1)
Requires-Dist: asyncio (==3.4.3)
Requires-Dist: bcrypt (==3.1.7)
Requires-Dist: bitarray
Requires-Dist: click (>=8.1.3)
Requires-Dist: colorama (==0.4.4)
Requires-Dist: cryptography (==36.0.2)
Requires-Dist: defusedxml (==0.7.1)
Requires-Dist: digitalpy (==0.3.13.7)
Requires-Dist: dnspython (==2.2.1)
Requires-Dist: eventlet (==0.33.1)
Requires-Dist: geographiclib (==1.52)
Requires-Dist: geopy (==2.2.0)
Requires-Dist: greenlet (==2.0.2)
Requires-Dist: itsdangerous (>=2.0.1)
Requires-Dist: lxml
Requires-Dist: monotonic (==1.6)
Requires-Dist: opentelemetry-sdk
Requires-Dist: pathlib2 (==2.3.7.post1)
Requires-Dist: pillow (==9.3.0)
Requires-Dist: protobuf (==3.18.3)
Requires-Dist: psutil (==5.9.4)
Requires-Dist: pyOpenSSL (==22.0.0)
Requires-Dist: pykml (==0.2.0)
Requires-Dist: pytak (==5.4.1) ; extra == "dev"
Requires-Dist: pytest (==7.2.0) ; extra == "dev"
Requires-Dist: pytest-asyncio (==0.20.1) ; extra == "dev"
Requires-Dist: python-engineio (==4.9.0)
Requires-Dist: python-socketio (==5.11.1)
Requires-Dist: pyzmq
Requires-Dist: qrcode (==7.3.1)
Requires-Dist: ruamel.yaml (==0.17.21)
Requires-Dist: ruamel.yaml.clib (==0.2.7)
Requires-Dist: six (==1.16.0)
Requires-Dist: tabulate (==0.8.7)
Requires-Dist: testresources (==2.0.1)
Requires-Dist: xmltodict
